FPGA.v
// Code your design here
// Entry Number : 2019CSB1095
// Lab 5: 1095 % 7 + 1 = 4
// 3 to 8 line decoder
// Lab 6: (1095%1)+1, (1095%1)+6, 4 = 1, 7, 4
// 3 to 8 line decoder + BCD Adder + Universal Shift Register

// logic_tile and switch_box_4x4 used directly from lab 4

module logic_tile(out, clock, in1, in2, in3, in4, in5);
  
  // mem is the configuration provided in testbench
  
  reg [32:0] mem;

  // for mux_control (mem[32]) and LUT (mem[31:0])
  
  input in1, in2, in3, in4, in5, clock;
  output out;
  
  // look up table
  
  reg lut_out;
  
  always @(in1, in2, in3, in4, in5, mem) begin
    case ({in5, in4, in3, in2, in1})
      5'b00000: lut_out = mem[0];
      5'b00001: lut_out = mem[1];
      5'b00010: lut_out = mem[2];
      5'b00011: lut_out = mem[3];
      5'b00100: lut_out = mem[4];
      5'b00101: lut_out = mem[5];
      5'b00110: lut_out = mem[6];
      5'b00111: lut_out = mem[7];
      5'b01000: lut_out = mem[8];
      5'b01001: lut_out = mem[9];
      5'b01010: lut_out = mem[10];
      5'b01011: lut_out = mem[11];
      5'b01100: lut_out = mem[12];
      5'b01101: lut_out = mem[13];
      5'b01110: lut_out = mem[14];
      5'b01111: lut_out = mem[15];
      5'b10000: lut_out = mem[16];
      5'b10001: lut_out = mem[17];
      5'b10010: lut_out = mem[18];
      5'b10011: lut_out = mem[19];
      5'b10100: lut_out = mem[20];
      5'b10101: lut_out = mem[21];
      5'b10110: lut_out = mem[22];
      5'b10111: lut_out = mem[23];
      5'b11000: lut_out = mem[24];
      5'b11001: lut_out = mem[25];
      5'b11010: lut_out = mem[26];
      5'b11011: lut_out = mem[27];
      5'b11100: lut_out = mem[28];
      5'b11101: lut_out = mem[29];
      5'b11110: lut_out = mem[30];
      5'b11111: lut_out = mem[31];
      default: lut_out = 1'bx;
    endcase
  end
  
  
  // flip flop
  
  reg flipflop_out;
  
  always @(posedge clock) begin
    flipflop_out <= lut_out;
  end
  

  // mux
  // 0 corresponds to combinational (without flip flop)
  // 1 corresponds to synchronous (with flip flop)
  
  reg out;
  
  always @(*) begin
    case ({mem[32]})
      1'b0: out = lut_out;
      1'b1: out = flipflop_out;
      default: out = 1'bx;
    endcase
  end
    
    
endmodule
        
  
  
module switch_box_4x4(out, in);
  
  input [3:0] in;
  output [3:0] out;

  // configure is the configuration provided in testbench

  
  reg [15:0] configure;
  
  assign out[0] = (in[0] & configure[0]) | (in[1] & configure[1]) | (in[2] & configure[2]) | (in[3] & configure[3]);

  assign out[1] = (in[0] & configure[4]) | (in[1] & configure[5]) | (in[2] & configure[6]) | (in[3] & configure[7]);

  assign out[2] = (in[0] & configure[8]) | (in[1] & configure[9]) | (in[2] & configure[10]) | (in[3] & configure[11]);

  assign out[3] = (in[0] & configure[12]) | (in[1] & configure[13]) | (in[2] & configure[14]) | (in[3] & configure[15]);


endmodule



module lab6(out, prev, in1, in2, in3, clock); //all out and in are 4 bits

  input [3:0] in1, in2, in3;
  input clock;
  input [7:0] prev;

  output [7:0] out;

//   reg [7:0] out;

  wire l0;
  wire t0, t1;

  assign t0 = 1'b0;
  assign t1 = 1'b0;

  wire [7:0] w1;

  wire [3:0] cs3;

//   logic_tile lt0a(.out(out[0]), .clock(clock), .in1(1'b0), .in2(in3[0]), .in3(in3[1]), .in4(in3[2]), .in5(1'b0));
  logic_tile lt0a(w1[0], clock, prev[0], in3[0], in3[1], in3[2], prev[1]);
  logic_tile lt1a(w1[1], clock, prev[1], prev[0], in3[1], in3[2], prev[2]);
  logic_tile lt2a(w1[2], clock, prev[2], prev[1], in3[1], in3[2], prev[3]);
  logic_tile lt3a(w1[3], clock, prev[3], prev[2], in3[1], in3[2], prev[4]);
  logic_tile lt4a(w1[4], clock, prev[4], prev[3], in3[1], in3[2], prev[5]);
  logic_tile lt5a(w1[5], clock, prev[5], prev[4], in3[1], in3[2], prev[6]);
  logic_tile lt6a(w1[6], clock, prev[6], prev[5], in3[1], in3[2], prev[7]);
  logic_tile lt7a(w1[7], clock, prev[7], prev[6], in3[1], in3[2], 1'b0);

  logic_tile lt0b(out[0], clock, in1[0], in1[1], w1[0], 1'b0, in3[3]);
  logic_tile lt1b(out[1], clock, in1[1], in1[0], w1[1], w1[0], in3[3]);
  logic_tile lt2b(cs3[0], clock, in1[2], in1[3], w1[2], 1'b0, in3[3]);
  logic_tile lt3b(out[3], clock, in1[3], in1[2], w1[3], w1[2], in3[3]);
  logic_tile lt4b(cs3[1], clock, in2[0], in2[1], w1[4], 1'b0, in3[3]);
  logic_tile lt5b(out[5], clock, in2[1], in2[0], w1[5], w1[4], in3[3]);
  logic_tile lt6b(cs3[2], clock, in2[2], in2[3], w1[6], 1'b0, in3[3]);
  logic_tile lt7b(cs3[3], clock, in2[3], in2[2], w1[7], w1[6], in3[3]);
  //assign out[0] = l0;
//   assign out[1] = l0;

  logic_tile s1(out[2], clock, 1'b0, cs3[0], cs3[1], cs3[2], cs3[3]);
  logic_tile s2(out[4], clock, 1'b0, cs3[0], cs3[1], cs3[2], cs3[3]);
  logic_tile s3(out[6], clock, 1'b0, cs3[0], cs3[1], cs3[2], cs3[3]);
  logic_tile co(out[7], clock, 1'b0, cs3[0], cs3[1], cs3[2], cs3[3]);


endmodule

testbench_usr.v
// Code your design here
// Entry Number : 2019CSB1095
// Lab 5: 1095 % 7 + 1 = 4
// 3 to 8 line decoder
// Lab 6: (1095%1)+1, (1095%1)+6, 4 = 1, 7, 4
// 3 to 8 line decoder + BCD Adder + Universal Shift Register

module lab6_tb();
  
  // initializing clock [T = 20] till t = 1000
  
  reg clock;
  
  initial
    clock = 1'b0;

  always
    #10 clock = !clock;

  initial
    #1000 $finish;
  
  
  // input form "configuration.mem" file
  
  reg [31:0]memory[42:0]; // array of size three, each entry of 32 bits
  initial begin
    $readmemh("conf_usr.mem", memory);
  end

  reg [3:0] rin1, rin2, rin3;
  wire [7:0] wout;

  reg [7:0] retain;

  initial 
    retain = 8'b00000000;
  always
    #20 retain = wout;
    

  lab6 inst_l6(.out(wout), .prev(retain), .in1(rin1), .in2(rin2), .in3(rin3), .clock(clock));
    initial
      begin

        // inst_l6.sb1.configure = {memory[0][15:0]};
        // inst_l6.sb2.configure = {memory[1][15:0]};
        // inst_l6.sb3.configure = {memory[2][15:0]};

        // inst_l6.s1b.configure = {memory[1][15:0]};
        // inst_l6.s2b.configure = {memory[2][15:0]};
        
        inst_l6.lt0a.mem = {memory[4][0], memory[3][31:0]};
        inst_l6.lt1a.mem = {memory[6][0], memory[5][31:0]};
        inst_l6.lt2a.mem = {memory[8][0], memory[7][31:0]};
        inst_l6.lt3a.mem = {memory[10][0], memory[9][31:0]};
        inst_l6.lt4a.mem = {memory[12][0], memory[11][31:0]};
        inst_l6.lt5a.mem = {memory[14][0], memory[13][31:0]};
        inst_l6.lt6a.mem = {memory[16][0], memory[15][31:0]};
        inst_l6.lt7a.mem = {memory[18][0], memory[17][31:0]};
        

        inst_l6.lt0b.mem = {memory[20][0], memory[19][31:0]};
        inst_l6.lt1b.mem = {memory[22][0], memory[21][31:0]};
        inst_l6.lt2b.mem = {memory[24][0], memory[23][31:0]};
        inst_l6.lt3b.mem = {memory[26][0], memory[25][31:0]};
        inst_l6.lt4b.mem = {memory[28][0], memory[27][31:0]};
        inst_l6.lt5b.mem = {memory[30][0], memory[29][31:0]};
        inst_l6.lt6b.mem = {memory[32][0], memory[31][31:0]};
        inst_l6.lt7b.mem = {memory[34][0], memory[33][31:0]};
        

        inst_l6.s1.mem = {memory[36][0], memory[35][31:0]};
        inst_l6.s2.mem = {memory[38][0], memory[37][31:0]};
        inst_l6.s3.mem = {memory[40][0], memory[39][31:0]};
        inst_l6.co.mem = {memory[42][0], memory[41][31:0]};
        

        rin1 = 4'b0011; // {B1, A1, B0, A0} 
        rin2 = 4'b0101; // {B3, A3, B2, A2}
        rin3 = 4'b1000; // {0, 0, 0, cin}
        #30
        $display("Load: %b%b", rin2, rin1);
        $display("SI: %b  Sh: %b  ShL: %b  L: %b",
        rin3[0], rin3[1], rin3[2], rin3[3]);
        $display("Output: %b", wout);

        rin1 = 4'b0011; // {B1, A1, B0, A0} 
        rin2 = 4'b1100; // {B3, A3, B2, A2}
        rin3 = 4'b0010; // {0, 0, 0, cin}
        #100
        $display("Load: %b%b", rin2, rin1);
        $display("SI: %b  Sh: %b  ShL: %b  L: %b",
        rin3[0], rin3[1], rin3[2], rin3[3]);
        $display("Output: %b", wout);
        
        rin1 = 4'b0011; // {B1, A1, B0, A0} 
        rin2 = 4'b1100; // {B3, A3, B2, A2}
        rin3 = 4'b0011; // {0, 0, 0, cin}
        #200
        $display("Load: %b%b", rin2, rin1);
        $display("SI: %b  Sh: %b  ShL: %b  L: %b",
        rin3[0], rin3[1], rin3[2], rin3[3]);
        $display("Output: %b", wout);

        rin1 = 4'b0011; // {B1, A1, B0, A0} 
        rin2 = 4'b1100; // {B3, A3, B2, A2}
        rin3 = 4'b0100; // {0, 0, 0, cin}
        #400
        $display("Load: %b%b", rin2, rin1);
        $display("SI: %b  Sh: %b  ShL: %b  L: %b",
        rin3[0], rin3[1], rin3[2], rin3[3]);
        $display("Output: %b", wout);

      end
      
  initial
    begin
      $dumpfile("wave_l6_usr.vcd");
      $dumpvars;
    end

endmodule

wave_l6_dec.vcd
$date
	Wed Nov 25 07:29:39 2020
$end
$version
	Icarus Verilog
$end
$timescale
	1s
$end
$scope module lab6_tb $end
$var wire 8 ! wout [7:0] $end
$var reg 1 " clock $end
$var reg 8 # retain [7:0] $end
$var reg 4 $ rin1 [3:0] $end
$var reg 4 % rin2 [3:0] $end
$var reg 4 & rin3 [3:0] $end
$scope module inst_l6 $end
$var wire 1 " clock $end
$var wire 4 ' in1 [3:0] $end
$var wire 4 ( in2 [3:0] $end
$var wire 4 ) in3 [3:0] $end
$var wire 8 * prev [7:0] $end
$var wire 1 + t0 $end
$var wire 1 , t1 $end
$var wire 8 - w1 [7:0] $end
$var wire 8 . out [7:0] $end
$var wire 4 / cs3 [3:0] $end
$scope module co $end
$var wire 1 " clock $end
$var wire 1 0 in1 $end
$var wire 1 1 in2 $end
$var wire 1 2 in3 $end
$var wire 1 3 in4 $end
$var wire 1 4 in5 $end
$var reg 1 5 flipflop_out $end
$var reg 1 6 lut_out $end
$var reg 33 7 mem [32:0] $end
$var reg 1 8 out $end
$upscope $end
$scope module lt0a $end
$var wire 1 " clock $end
$var wire 1 9 in1 $end
$var wire 1 : in2 $end
$var wire 1 ; in3 $end
$var wire 1 < in4 $end
$var wire 1 = in5 $end
$var reg 1 > flipflop_out $end
$var reg 1 ? lut_out $end
$var reg 33 @ mem [32:0] $end
$var reg 1 A out $end
$upscope $end
$scope module lt0b $end
$var wire 1 " clock $end
$var wire 1 B in1 $end
$var wire 1 C in2 $end
$var wire 1 D in3 $end
$var wire 1 E in4 $end
$var wire 1 F in5 $end
$var reg 1 G flipflop_out $end
$var reg 1 H lut_out $end
$var reg 33 I mem [32:0] $end
$var reg 1 J out $end
$upscope $end
$scope module lt1a $end
$var wire 1 " clock $end
$var wire 1 K in1 $end
$var wire 1 L in2 $end
$var wire 1 M in3 $end
$var wire 1 N in4 $end
$var wire 1 O in5 $end
$var reg 1 P flipflop_out $end
$var reg 1 Q lut_out $end
$var reg 33 R mem [32:0] $end
$var reg 1 S out $end
$upscope $end
$scope module lt1b $end
$var wire 1 " clock $end
$var wire 1 T in1 $end
$var wire 1 U in2 $end
$var wire 1 V in3 $end
$var wire 1 W in4 $end
$var wire 1 X in5 $end
$var reg 1 Y flipflop_out $end
$var reg 1 Z lut_out $end
$var reg 33 [ mem [32:0] $end
$var reg 1 \ out $end
$upscope $end
$scope module lt2a $end
$var wire 1 " clock $end
$var wire 1 ] in1 $end
$var wire 1 ^ in2 $end
$var wire 1 _ in3 $end
$var wire 1 ` in4 $end
$var wire 1 a in5 $end
$var reg 1 b flipflop_out $end
$var reg 1 c lut_out $end
$var reg 33 d mem [32:0] $end
$var reg 1 e out $end
$upscope $end
$scope module lt2b $end
$var wire 1 " clock $end
$var wire 1 f in1 $end
$var wire 1 g in2 $end
$var wire 1 h in3 $end
$var wire 1 i in4 $end
$var wire 1 j in5 $end
$var reg 1 k flipflop_out $end
$var reg 1 l lut_out $end
$var reg 33 m mem [32:0] $end
$var reg 1 n out $end
$upscope $end
$scope module lt3a $end
$var wire 1 " clock $end
$var wire 1 o in1 $end
$var wire 1 p in2 $end
$var wire 1 q in3 $end
$var wire 1 r in4 $end
$var wire 1 s in5 $end
$var reg 1 t flipflop_out $end
$var reg 1 u lut_out $end
$var reg 33 v mem [32:0] $end
$var reg 1 w out $end
$upscope $end
$scope module lt3b $end
$var wire 1 " clock $end
$var wire 1 x in1 $end
$var wire 1 y in2 $end
$var wire 1 z in3 $end
$var wire 1 { in4 $end
$var wire 1 | in5 $end
$var reg 1 } flipflop_out $end
$var reg 1 ~ lut_out $end
$var reg 33 !" mem [32:0] $end
$var reg 1 "" out $end
$upscope $end
$scope module lt4a $end
$var wire 1 " clock $end
$var wire 1 #" in1 $end
$var wire 1 $" in2 $end
$var wire 1 %" in3 $end
$var wire 1 &" in4 $end
$var wire 1 '" in5 $end
$var reg 1 (" flipflop_out $end
$var reg 1 )" lut_out $end
$var reg 33 *" mem [32:0] $end
$var reg 1 +" out $end
$upscope $end
$scope module lt4b $end
$var wire 1 " clock $end
$var wire 1 ," in1 $end
$var wire 1 -" in2 $end
$var wire 1 ." in3 $end
$var wire 1 /" in4 $end
$var wire 1 0" in5 $end
$var reg 1 1" flipflop_out $end
$var reg 1 2" lut_out $end
$var reg 33 3" mem [32:0] $end
$var reg 1 4" out $end
$upscope $end
$scope module lt5a $end
$var wire 1 " clock $end
$var wire 1 5" in1 $end
$var wire 1 6" in2 $end
$var wire 1 7" in3 $end
$var wire 1 8" in4 $end
$var wire 1 9" in5 $end
$var reg 1 :" flipflop_out $end
$var reg 1 ;" lut_out $end
$var reg 33 <" mem [32:0] $end
$var reg 1 =" out $end
$upscope $end
$scope module lt5b $end
$var wire 1 " clock $end
$var wire 1 >" in1 $end
$var wire 1 ?" in2 $end
$var wire 1 @" in3 $end
$var wire 1 A" in4 $end
$var wire 1 B" in5 $end
$var reg 1 C" flipflop_out $end
$var reg 1 D" lut_out $end
$var reg 33 E" mem [32:0] $end
$var reg 1 F" out $end
$upscope $end
$scope module lt6a $end
$var wire 1 " clock $end
$var wire 1 G" in1 $end
$var wire 1 H" in2 $end
$var wire 1 I" in3 $end
$var wire 1 J" in4 $end
$var wire 1 K" in5 $end
$var reg 1 L" flipflop_out $end
$var reg 1 M" lut_out $end
$var reg 33 N" mem [32:0] $end
$var reg 1 O" out $end
$upscope $end
$scope module lt6b $end
$var wire 1 " clock $end
$var wire 1 P" in1 $end
$var wire 1 Q" in2 $end
$var wire 1 R" in3 $end
$var wire 1 S" in4 $end
$var wire 1 T" in5 $end
$var reg 1 U" flipflop_out $end
$var reg 1 V" lut_out $end
$var reg 33 W" mem [32:0] $end
$var reg 1 X" out $end
$upscope $end
$scope module lt7a $end
$var wire 1 " clock $end
$var wire 1 Y" in1 $end
$var wire 1 Z" in2 $end
$var wire 1 [" in3 $end
$var wire 1 \" in4 $end
$var wire 1 ]" in5 $end
$var reg 1 ^" flipflop_out $end
$var reg 1 _" lut_out $end
$var reg 33 `" mem [32:0] $end
$var reg 1 a" out $end
$upscope $end
$scope module lt7b $end
$var wire 1 " clock $end
$var wire 1 b" in1 $end
$var wire 1 c" in2 $end
$var wire 1 d" in3 $end
$var wire 1 e" in4 $end
$var wire 1 f" in5 $end
$var reg 1 g" flipflop_out $end
$var reg 1 h" lut_out $end
$var reg 33 i" mem [32:0] $end
$var reg 1 j" out $end
$upscope $end
$scope module s1 $end
$var wire 1 " clock $end
$var wire 1 k" in1 $end
$var wire 1 l" in2 $end
$var wire 1 m" in3 $end
$var wire 1 n" in4 $end
$var wire 1 o" in5 $end
$var reg 1 p" flipflop_out $end
$var reg 1 q" lut_out $end
$var reg 33 r" mem [32:0] $end
$var reg 1 s" out $end
$upscope $end
$scope module s2 $end
$var wire 1 " clock $end
$var wire 1 t" in1 $end
$var wire 1 u" in2 $end
$var wire 1 v" in3 $end
$var wire 1 w" in4 $end
$var wire 1 x" in5 $end
$var reg 1 y" flipflop_out $end
$var reg 1 z" lut_out $end
$var reg 33 {" mem [32:0] $end
$var reg 1 |" out $end
$upscope $end
$scope module s3 $end
$var wire 1 " clock $end
$var wire 1 }" in1 $end
$var wire 1 ~" in2 $end
$var wire 1 !# in3 $end
$var wire 1 "# in4 $end
$var wire 1 ## in5 $end
$var reg 1 $# flipflop_out $end
$var reg 1 %# lut_out $end
$var reg 33 &# mem [32:0] $end
$var reg 1 '# out $end
$upscope $end
$upscope $end
$upscope $end
$scope module switch_box_4x4 $end
$var wire 4 (# in [3:0] $end
$var wire 4 )# out [3:0] $end
$var reg 16 *# configure [15:0] $end
$upscope $end
$enddefinitions $end
#0
$dumpvars
bx *#
bx )#
bz (#
0'#
b11111111000000001111111100000000 &#
0%#
x$#
0##
0"#
0!#
0~"
0}"
0|"
b11110000111100001111000011110000 {"
0z"
xy"
0x"
0w"
0v"
0u"
0t"
0s"
b11001100110011001100110011001100 r"
0q"
xp"
0o"
0n"
0m"
0l"
0k"
0j"
b10000000000000000000 i"
0h"
xg"
0f"
0e"
0d"
0c"
0b"
0a"
b0 `"
0_"
x^"
0]"
0\"
0["
0Z"
0Y"
0X"
b1000000000000000000 W"
0V"
xU"
0T"
0S"
0R"
0Q"
0P"
0O"
b0 N"
0M"
xL"
0K"
0J"
0I"
0H"
0G"
0F"
b1000000000000000000 E"
0D"
xC"
0B"
0A"
0@"
0?"
0>"
0="
b0 <"
0;"
x:"
09"
08"
07"
06"
05"
04"
b10000000000000000 3"
02"
x1"
00"
0/"
0."
0-"
0,"
0+"
b0 *"
0)"
x("
0'"
0&"
0%"
0$"
0#"
0""
b1000 !"
0~
x}
0|
0{
0z
0y
0x
0w
b0 v
0u
xt
0s
0r
0q
0p
0o
0n
b100 m
0l
xk
0j
0i
0h
0g
0f
0e
b0 d
0c
xb
0a
0`
0_
0^
0]
0\
b100 [
0Z
xY
0X
0W
0V
0U
0T
0S
b0 R
0Q
xP
0O
0N
0M
0L
0K
1J
b1 I
1H
xG
0F
0E
0D
0C
0B
0A
b0 @
0?
x>
0=
0<
0;
0:
09
08
b11111111111111110000000000000000 7
06
x5
04
03
02
01
00
b0 /
b1 .
b0 -
0,
0+
b0 *
b0 )
b0 (
b0 '
b0 &
b0 %
b0 $
b0 #
0"
b1 !
$end
#10
0>
0P
0b
0t
0("
0:"
0L"
0^"
1G
0Y
0k
0}
01"
0C"
0U"
0g"
0p"
0y"
0$#
05
1"
#20
19
1L
0"
b1 #
b1 *
#25
0J
b10 !
b10 .
1\
0H
1Z
1,"
1?"
1P"
1c"
1B
1U
1f
1y
b101 %
b101 (
b101 $
b101 '
#30
1Y
0G
1"
#40
09
1=
1K
0L
1^
0"
b10 #
b10 *
#50
1s"
1q"
1l"
1u"
1~"
11
b100 !
b100 .
0\
b1 /
1n
0Z
1l
0,"
1-"
1>"
0?"
0P"
1Q"
1b"
0c"
0B
1C
1T
0U
0f
1g
1x
0y
1"
b1010 %
b1010 (
b1010 $
b1010 '
#60
0=
0K
1O
1]
0^
1p
0"
b100 #
b100 *
#70
1p"
1k
0Y
1"
#75
0s"
0q"
0l"
0u"
0~"
01
b0 /
0n
b1000 !
b1000 .
1""
0l
1~
1,"
1?"
1P"
1c"
1B
1U
1f
1y
b1111 %
b1111 (
b1111 $
b1111 '
#80
0O
0]
1a
1o
0p
1$"
0"
b1000 #
b1000 *
#90
0k
1}
0p"
1"
#100
1|"
1z"
1m"
1v"
1!#
12
b10 /
14"
b10000 !
b10000 .
0""
12"
0~
1F
1X
1j
1|
10"
1B"
1T"
1f"
0,"
0-"
0>"
0?"
0P"
0Q"
0b"
0c"
0B
0C
0T
0U
0f
0g
0x
0y
0"
b1000 &
b1000 )
b0 %
b0 (
b0 $
b0 '
#110
1y"
11"
0}
1"
#120
0a
0o
1s
1#"
0$"
16"
0"
b10000 #
b10000 *
#125
0|"
0z"
0m"
0v"
0!#
02
b0 /
04"
b100000 !
b100000 .
1F"
02"
1D"
1,"
1?"
1P"
1c"
1B
1U
1f
1y
b101 %
b101 (
b101 $
b101 '
#130
01"
1C"
0y"
1"
#140
0s
0#"
1'"
15"
06"
1H"
0"
b100000 #
b100000 *
#150
1'#
1%#
1n"
1w"
1"#
13
b1000000 !
b1000000 .
0F"
b100 /
1X"
0D"
1V"
0,"
1-"
1>"
0?"
0P"
1Q"
1b"
0c"
0B
1C
1T
0U
0f
1g
1x
0y
1"
b1010 %
b1010 (
b1010 $
b1010 '
#160
0'"
05"
19"
1G"
0H"
1Z"
0"
b1000000 #
b1000000 *
#170
0C"
1U"
1$#
1"
#175
0'#
b10000000 !
b10000000 .
18
0%#
16
0n"
0w"
0"#
03
1o"
1x"
1##
14
0X"
b1000 /
1j"
0V"
1h"
1,"
1?"
1P"
1c"
1B
1U
1f
1y
b1111 %
b1111 (
b1111 $
b1111 '
#180
09"
0G"
1K"
1Y"
0Z"
0"
b10000000 #
b10000000 *
#190
15
0$#
1g"
0U"
1"
